exonum_precheck/__init__.py
exonum_precheck/__main__.py
exonum_precheck/precheck.py
exonum_precheck-0.1.5.dist-info/LICENSE
exonum_precheck-0.1.5.dist-info/METADATA
exonum_precheck-0.1.5.dist-info/WHEEL
exonum_precheck-0.1.5.dist-info/top_level.txt
exonum_precheck-0.1.5.dist-info/RECORD
