Metadata-Version: 2.1
Name: exonum-precheck
Version: 0.1.5
Summary: Exonum precheck deployment script
Home-page: https://github.com/popzxc/exonum_precheck
Author: Igor Aleksanov
License: UNKNOWN
Platform: UNKNOWN
Classifier: Programming Language :: Python :: 3
Classifier: License :: OSI Approved :: MIT License
Classifier: Operating System :: OS Independent
Classifier: Topic :: Security :: Cryptography
Requires-Python: >=3.4
Requires-Dist: pyyaml
